ABCDanalysis.py
ABCDanalysis-0.0.1.dist-info/METADATA
ABCDanalysis-0.0.1.dist-info/WHEEL
ABCDanalysis-0.0.1.dist-info/top_level.txt
ABCDanalysis-0.0.1.dist-info/RECORD
