Metadata-Version: 2.1
Name: ABCDanalysis
Version: 0.0.1
Summary: analysis the ABCD dataset to predict mental health issue
Home-page: UNKNOWN
License: UNKNOWN
Platform: UNKNOWN
Requires-Dist: Pandas
